[{"chat_verbose": "I'm a\nI was born in January 1991\nMy postal code is [input:Field id:0] A1A 1A1\nPlease name the object in the picture, in one word", "context_path": "", "floor_path": null, "id": "@@@7@@@716@@@216@@@1140@@@375", "ielements": [{"actionType": null, "path": "body > div > div > section > div > div > div > div:nth-child(5) > type-input-dir > h5 > span:nth-child(2) > input"}], "is_media_group": false, "search_verbose": "I'm a I was born in January 1991 My postal code is A1A 1A1 Please name the object in the picture, in one word"}, {"chat_verbose": "Privacy Policy [input:Select id:0]", "context_path": "", "floor_path": null, "id": "@@@2@@@1218@@@1289@@@105@@@19", "ielements": [{"actionType": null, "path": "body > div > div > footer > div > p > a > i"}], "is_media_group": false, "search_verbose": "Privacy Policy"}]